{
	"cmake" : 
	{
		"generator" : 
		{
			"multiConfig" : false,
			"name" : "MinGW Makefiles"
		},
		"paths" : 
		{
			"cmake" : "C:/Program Files/CMake/bin/cmake.exe",
			"cpack" : "C:/Program Files/CMake/bin/cpack.exe",
			"ctest" : "C:/Program Files/CMake/bin/ctest.exe",
			"root" : "C:/Program Files/CMake/share/cmake-4.0"
		},
		"version" : 
		{
			"isDirty" : false,
			"major" : 4,
			"minor" : 0,
			"patch" : 0,
			"string" : "4.0.0-rc4",
			"suffix" : "rc4"
		}
	},
	"objects" : 
	[
		{
			"jsonFile" : "codemodel-v2-8cac96527c976e7d54ad.json",
			"kind" : "codemodel",
			"version" : 
			{
				"major" : 2,
				"minor" : 8
			}
		},
		{
			"jsonFile" : "cache-v2-4c1eda3cbf0b5afb82f9.json",
			"kind" : "cache",
			"version" : 
			{
				"major" : 2,
				"minor" : 0
			}
		},
		{
			"jsonFile" : "cmakeFiles-v1-84510a70f145a0ae70f2.json",
			"kind" : "cmakeFiles",
			"version" : 
			{
				"major" : 1,
				"minor" : 1
			}
		},
		{
			"jsonFile" : "toolchains-v1-67228bb07a5f6c90d582.json",
			"kind" : "toolchains",
			"version" : 
			{
				"major" : 1,
				"minor" : 0
			}
		}
	],
	"reply" : 
	{
		"client-vscode" : 
		{
			"query.json" : 
			{
				"requests" : 
				[
					{
						"kind" : "cache",
						"version" : 2
					},
					{
						"kind" : "codemodel",
						"version" : 2
					},
					{
						"kind" : "toolchains",
						"version" : 1
					},
					{
						"kind" : "cmakeFiles",
						"version" : 1
					}
				],
				"responses" : 
				[
					{
						"jsonFile" : "cache-v2-4c1eda3cbf0b5afb82f9.json",
						"kind" : "cache",
						"version" : 
						{
							"major" : 2,
							"minor" : 0
						}
					},
					{
						"jsonFile" : "codemodel-v2-8cac96527c976e7d54ad.json",
						"kind" : "codemodel",
						"version" : 
						{
							"major" : 2,
							"minor" : 8
						}
					},
					{
						"jsonFile" : "toolchains-v1-67228bb07a5f6c90d582.json",
						"kind" : "toolchains",
						"version" : 
						{
							"major" : 1,
							"minor" : 0
						}
					},
					{
						"jsonFile" : "cmakeFiles-v1-84510a70f145a0ae70f2.json",
						"kind" : "cmakeFiles",
						"version" : 
						{
							"major" : 1,
							"minor" : 1
						}
					}
				]
			}
		}
	}
}
